chem_dcat_ap/__init__.py
chem_dcat_ap/_version.py
chem_dcat_ap/datamodel/__init__.py
chem_dcat_ap/datamodel/chem_dcat_ap.py
chem_dcat_ap/datamodel/chem_dcat_ap_pydantic.py
chem_dcat_ap/schema/README.md
chem_dcat_ap/schema/chem_dcat_ap.yaml
chem_dcat_ap/schema/chemical_entities_ap.yaml
chem_dcat_ap/schema/chemical_reaction_ap.yaml
chem_dcat_ap/schema/material_entities_ap.yaml
chem_dcat_ap-0.1.0rc1.dist-info/METADATA
chem_dcat_ap-0.1.0rc1.dist-info/WHEEL
chem_dcat_ap-0.1.0rc1.dist-info/licenses/LICENSE
chem_dcat_ap-0.1.0rc1.dist-info/RECORD
