Metadata-Version: 2.4
Name: chem-dcat-ap
Version: 0.1.0rc1
Summary: An extension of the DCAT Application Profile extended to provide chemistry specific specific metadata for datasets.
Author-email: David Linke <david.linke@catalysis.de>, Philip Strömert <philip.stroemert@tib.eu>
License-Expression: MIT
License-File: LICENSE
Requires-Python: <4.0,>=3.9
Requires-Dist: linkml-runtime>=1.9.4
